<?xml version="1.0" encoding="utf-8"?>
<resources>
    <style name="myTextView" >
        <!--<item name="속성명">속성값</item>-->
        <item name="android:layout_width">wrap_content</item>
        <item name="android:layout_height">wrap_content</item>
        <item name="android:text">"그림판"</item>
        <item name="android:textColor">@color/title</item>
        <item name="android:textSize">30sp</item>
        <item name="android:textStyle">bold</item>
        <item name="android:layout_gravity">center</item>
        <item name="android:layout_marginTop">3dp</item>
        <item name="android:layout_marginBottom">3dp</item>
    </style>
</resources>